commonconf/VERSION
commonconf/__init__.py
commonconf/backends.py
commonconf/exceptions.py
commonconf/proxy.py
commonconf/test.py
commonconf/util.py
commonconf/backend/__init__.py
commonconf/backend/django.py
commonconf/backend/parser.py
commonconf/tests/__init__.py
commonconf/tests/test_configparser.py
commonconf/tests/test_django.py
commonconf/tests/test_override.py
commonconf/tests/files/sections.cfg
commonconf-1.2.2.dist-info/licenses/LICENSE
commonconf-1.2.2.dist-info/METADATA
commonconf-1.2.2.dist-info/WHEEL
commonconf-1.2.2.dist-info/top_level.txt
commonconf-1.2.2.dist-info/RECORD
