Metadata-Version: 2.4
Name: CommonConf
Version: 1.2.2
Summary: An interface for getting settings from a variety of configuration libraries.
Home-page: https://github.com/uw-it-aca/commonconf
Author: UW-IT SETS
Author-email: aca-it@uw.edu
License: Apache License, Version 2.0
Classifier: Intended Audience :: Developers
Classifier: License :: OSI Approved :: Apache Software License
Classifier: Operating System :: OS Independent
Classifier: Programming Language :: Python
License-File: LICENSE
Dynamic: author
Dynamic: author-email
Dynamic: classifier
Dynamic: description
Dynamic: home-page
Dynamic: license
Dynamic: license-file
Dynamic: summary
